{"cameraMode":{"drawMode":0,"name":"Shaded","section":"Shading Mode"},"sceneLighting":false,"audioPlay":false,"sceneViewState":{"m_AlwaysRefresh":false,"showFog":true,"showSkybox":true,"showFlares":true,"showImageEffects":true,"showParticleSystems":true,"showVisualEffectGraphs":true,"m_FxEnabled":true},"in2DMode":false,"pivot":{"x":-7.723406791687012,"y":1.906761646270752,"z":1.391911506652832},"rotation":{"x":0.052085667848587039,"y":0.9361732602119446,"z":-0.31004220247268679,"w":0.1573178768157959},"size":4.439674377441406,"orthographic":false}